tracklater/__init__.py
tracklater/database.py
tracklater/example_settings.json
tracklater/main.py
tracklater/models.py
tracklater/settings_utils.py
tracklater/test_settings.py
tracklater/utils.py
tracklater/views.py
tracklater/static/daytimeline.vue.js
tracklater/static/home.vue.js
tracklater/static/index.html
tracklater/static/timeline.vue.js
tracklater/static/toolbar.vue.js
tracklater/tests/__init__.py
tracklater/tests/conftest.py
tracklater/tests/test_app.py
tracklater/tests/test_gitmodule.py
tracklater/tests/test_jira.py
tracklater/tests/test_main.py
tracklater/tests/test_slack.py
tracklater/tests/test_taiga.py
tracklater/tests/test_thyme.py
tracklater/tests/test_toggl.py
tracklater/timemodules/__init__.py
tracklater/timemodules/clockify.py
tracklater/timemodules/github.py
tracklater/timemodules/gitmodule.py
tracklater/timemodules/interfaces.py
tracklater/timemodules/jira.py
tracklater/timemodules/slack.py
tracklater/timemodules/taiga.py
tracklater/timemodules/thyme.py
tracklater/timemodules/toggl.py
tracklater/timemodules/fixture/git_test_data.json
tracklater/timemodules/fixture/search_results.json
tracklater/timemodules/fixture/search_results_2.json
tracklater-1.6.1.dist-info/LICENSE
tracklater-1.6.1.dist-info/METADATA
tracklater-1.6.1.dist-info/WHEEL
tracklater-1.6.1.dist-info/entry_points.txt
tracklater-1.6.1.dist-info/top_level.txt
tracklater-1.6.1.dist-info/RECORD
