Metadata-Version: 2.1
Name: tracklater
Version: 1.6.1
Summary: TrackLater helps you track time after-the-fact by combining clues and showingyour day on a simple timeline view.
Home-page: https://github.com/Eerovil/TrackLater
Author: Eero Vilpponen
Author-email: eero.vilpponen@gmail.com
License: UNKNOWN
Platform: UNKNOWN
Classifier: Programming Language :: Python :: 3.7
Classifier: License :: OSI Approved :: MIT License
Classifier: Operating System :: OS Independent
Requires-Python: >=3.7.1
Requires-Dist: Flask (==1.0.3)
Requires-Dist: GitPython (==2.1.11)
Requires-Dist: gitdb2 (==3.0.1)
Requires-Dist: python-dateutil (==2.8.0)
Requires-Dist: slackclient (==2.0.1)
Requires-Dist: pytz (==2019.1)
Requires-Dist: flask-sqlalchemy (==2.4.0)
Requires-Dist: requests (==2.22.0)
Requires-Dist: appdirs (==1.4.3)
